[
	{"id": 1, "date": "1.2.2018", "title":"Nuorten SM-kilpailut 2018", "description":"Saara Mattila oli kolmas N15-sarjassa."},
	{"id": 2, "date": "1.3.2018", "title":"Veteraanien ampumahiihdon SM-2018 ja kansallinen pikakisa, Mikkeli"},
	{"id": 3, "date": "1.5.2018", "title":"Ampumasuunnistuksen SM-2018, Kauhava", "description":"Alahärmän Kisa järjesti ampumasuunnistuksen Suomen ja Sotilasurheiluliiton mestaruuskilpailut Kauhavan Alahärmässä."},
	{"id": 4, "date": "1.7.2018", "title":"HaHan kansallisen AJ-kisan kuvia", "description":"Kesä 2018"}
]